intrasom/__init__.py
intrasom/clustering.py
intrasom/codebook.py
intrasom/intrasom.py
intrasom/nonsupervised_eval.py
intrasom/object_functions.py
intrasom/visualization.py
intrasom/images/Foot_logo_fundo_branco.svg
intrasom/images/Logo_fundo_branco.svg
intrasom/images/cluster1.jpg
intrasom/images/cluster2.jpg
intrasom/images/cluster3.jpg
intrasom/images/component_plots.jpg
intrasom/images/foot.jpg
intrasom/images/foot3.jpg
intrasom/images/framework.png
intrasom/images/umatrix.jpg
intrasom/images/umatrix_labels.jpg
intrasom/images/umatrix_template.jpg
intrasom-1.0.4.4.dist-info/licenses/LICENSE
intrasom-1.0.4.4.dist-info/METADATA
intrasom-1.0.4.4.dist-info/WHEEL
intrasom-1.0.4.4.dist-info/top_level.txt
intrasom-1.0.4.4.dist-info/RECORD
