Metadata-Version: 2.4
Name: IntraSOM
Version: 1.0.4.4
Summary: IntraSOM: Library for Self-Organizing Maps with missing data, hexagonal lattice and toroidal projection
Author: InTRA RDI Center (Universidade de São Paulo)
Author-email: intra@usp.br
Keywords: Intrasom SOM Self-Organization Kohonen Non-Supervised U-Matrix
License-File: LICENSE
Requires-Dist: matplotlib>=3.7.1
Requires-Dist: scipy>=1.10.1
Requires-Dist: joblib>=1.2.0
Requires-Dist: scikit-learn>=1.2.2
Requires-Dist: pandas>=2.0.1
Requires-Dist: tqdm>=4.65.0
Requires-Dist: plotly>=5.14.1
Requires-Dist: scikit-image>=0.20.0
Requires-Dist: pyarrow>=9.0.0
Requires-Dist: openpyxl>=3.1.2
Requires-Dist: pyarrow>=9.0.0
Requires-Dist: openpyxl>=3.1.2
Requires-Dist: ipywidgets>=8.0.6
Requires-Dist: shapely>=2.0.1
Requires-Dist: geopandas>=0.13.0
Requires-Dist: nbformat>=5.9.0
Dynamic: author
Dynamic: author-email
Dynamic: description
Dynamic: description-content-type
Dynamic: keywords
Dynamic: license-file
Dynamic: requires-dist
Dynamic: summary
